MANIFEST.in
README.md
setup.cfg
setup.py
segmentify/__init__.py
segmentify/_key_bindings.py
segmentify/gui.py
segmentify/util.py
segmentify.egg-info/PKG-INFO
segmentify.egg-info/SOURCES.txt
segmentify.egg-info/dependency_links.txt
segmentify.egg-info/requires.txt
segmentify.egg-info/top_level.txt
segmentify/instances/__init__.py
segmentify/instances/main.py
segmentify/model/__init__.py
segmentify/model/unet.py
segmentify/model/layers/__init__.py
segmentify/model/layers/identity.py
segmentify/model/layers/unet_layers.py
segmentify/model/saved_model/HPA.pth
segmentify/model/saved_model/HPA_3.pth
segmentify/model/saved_model/HPA_4.pth
segmentify/model/saved_model/Nuclei.pth
segmentify/semantic/__init__.py
segmentify/semantic/main.py